pyjourney/__init__.py
pyjourney/api.py
pyjourney/exceptions.py
pyjourney/models.py
pyjourney-0.1.7.dist-info/METADATA
pyjourney-0.1.7.dist-info/WHEEL
pyjourney-0.1.7.dist-info/RECORD
